djangoldp/__init__.py
djangoldp/admin.py
djangoldp/apps.py
djangoldp/check_integrity.py
djangoldp/cli.py
djangoldp/etag.py
djangoldp/factories.py
djangoldp/fields.py
djangoldp/filters.py
djangoldp/middleware.py
djangoldp/pagination.py
djangoldp/parsers.py
djangoldp/permissions.py
djangoldp/related.py
djangoldp/renderers.py
djangoldp/serializers.py
djangoldp/urls.py
djangoldp/utils.py
djangoldp/activities/__init__.py
djangoldp/activities/errors.py
djangoldp/activities/objects.py
djangoldp/activities/services.py
djangoldp/activities/verbs.py
djangoldp/conf/__init__.py
djangoldp/conf/default_settings.py
djangoldp/conf/ldpsettings.py
djangoldp/conf/package_template/README.md
djangoldp/conf/package_template/setup.cfg
djangoldp/conf/package_template/setup.py-tpl
djangoldp/conf/package_template/app_name/__init__.py-tpl
djangoldp/conf/package_template/app_name/admin.py-tpl
djangoldp/conf/package_template/app_name/apps.py-tpl
djangoldp/conf/package_template/app_name/djangoldp_settings.py-tpl
djangoldp/conf/package_template/app_name/djangoldp_urls.py-tpl
djangoldp/conf/package_template/app_name/models.py-tpl
djangoldp/conf/package_template/app_name/tests.py-tpl
djangoldp/conf/package_template/app_name/views.py-tpl
djangoldp/conf/server_template/manage.py-tpl
djangoldp/conf/server_template/settings.yml
djangoldp/conf/server_template/server/__init__.py-tpl
djangoldp/conf/server_template/server/urls.py-tpl
djangoldp/conf/server_template/server/wsgi.py-tpl
djangoldp/endpoints/__init__.py
djangoldp/endpoints/webfinger.py
djangoldp/management/__init__.py
djangoldp/management/commands/__init__.py
djangoldp/management/commands/check_integrity.py
djangoldp/management/commands/configure.py
djangoldp/management/commands/federate.py
djangoldp/management/commands/generate_static_content.py
djangoldp/management/commands/mock_user.py
djangoldp/migrations/0001_initial.py
djangoldp/migrations/0002_auto_20190906_0642.py
djangoldp/migrations/0003_auto_20190911_0931.py
djangoldp-5.0.1.dist-info/licenses/LICENSE
djangoldp-5.0.1.dist-info/METADATA
djangoldp-5.0.1.dist-info/WHEEL
djangoldp-5.0.1.dist-info/entry_points.txt
djangoldp-5.0.1.dist-info/top_level.txt
djangoldp-5.0.1.dist-info/RECORD
