Metadata-Version: 2.4
Name: djangoldp
Version: 5.0.1
Summary: Linked Data Platform interface for Django Rest Framework
Home-page: https://git.startinblox.com/djangoldp-packages/djangoldp/
Author: Startin'blox
Author-email: tech@startinblox.com
License: MIT
Requires-Python: >=3.10
License-File: LICENSE
Requires-Dist: django<6.0,>=5.2.0
Requires-Dist: validators~=0.20.0
Requires-Dist: pyld~=1.0.0
Requires-Dist: django-guardian~=2.4.0
Requires-Dist: djangorestframework<3.16.0,>=3.14.0
Requires-Dist: drf-spectacular<0.28.0,>=0.24.0
Requires-Dist: requests~=2.31.0
Requires-Dist: pyyaml~=6.0.0
Requires-Dist: click~=8.1.0
Requires-Dist: django-brotli~=0.2.0
Requires-Dist: djangorestframework-guardian~=0.3.0
Requires-Dist: Faker~=14.2.0
Requires-Dist: rdflib>=6.0.0
Provides-Extra: dev
Requires-Dist: validators; extra == "dev"
Requires-Dist: factory_boy>=2.11.0; extra == "dev"
Provides-Extra: crypto
Requires-Dist: pycryptodomex~=3.10; extra == "crypto"
Dynamic: license-file
